{
	"model": {
		"modelName": "New model",
		"dbVersion": "v2",
		"dbVendor": "BigQuery"
	},
	"container": {
		"name": "New_dataset",
		"unlimitedQuota": false
	},
	"collection": {
		"collectionName": "New table"
	},
	"field": {
		"name": "New_column"
	},
	"patternField": {
		"name": "^[a-zA-Z0-9_.-]+$"
	},
	"multipleField": {
		"primaryKey": false
	},
	"subschema": {},
	"arrayItem": {},
	"choice": {},
	"relationship": {},
	"user": {},
	"view": {
		"name": "New_view",
		"viewOn": "",
		"pipeline": "",
		"autoSortKey": false
	}
}